{
  "links": [
    {
      "id": "55a1233b1e",
      "qrData": "/u/55a1233b1e",
      "sourceDocumentNumber": "AWZ-2026-00323",
      "isApiCreated": false,
      "createdAt": "2026-04-02T14:23:33.286Z"
    },
    {
      "id": "e3fe5824f4",
      "qrData": "/u/e3fe5824f4",
      "sourceDocumentNumber": "rrr",
      "isApiCreated": false,
      "createdAt": "2026-04-02T18:47:23.453Z"
    }
  ],
  "photos": [
    {
      "id": "358638f4-3337-44d3-b30f-88739299799b",
      "linkId": "55a1233b1e",
      "filename": "1775139942689-217780856.png",
      "contentType": "image/png",
      "filePath": "C:\\Users\\pciecierski\\Documents\\QRupload\\uploads\\55a1233b1e\\1775139942689-217780856.png",
      "createdAt": "2026-04-02T14:25:42.693Z"
    },
    {
      "id": "38ce5a33-83a4-4c27-bda2-b1ae4ce7440d",
      "linkId": "55a1233b1e",
      "filename": "1775154663530-324646561.png",
      "contentType": "image/png",
      "filePath": "C:\\Users\\pciecierski\\Documents\\QRupload\\uploads\\55a1233b1e\\1775154663530-324646561.png",
      "createdAt": "2026-04-02T18:31:03.535Z"
    }
  ]
}